eryx_deploy/__init__.py
eryx_deploy/_legacy_migrate_db.py
eryx_deploy/default_config.py
eryx_deploy/app_stacks/__init__.py
eryx_deploy/app_stacks/abs_app_stack.py
eryx_deploy/app_stacks/django_basic_stack.py
eryx_deploy/app_stacks/ruby_on_rails_stack.py
eryx_deploy/assets/__init__.py
eryx_deploy/assets/abs_executable_environment.py
eryx_deploy/assets/databases/__init__.py
eryx_deploy/assets/databases/abs_database.py
eryx_deploy/assets/databases/mysql.py
eryx_deploy/assets/databases/postgresql.py
eryx_deploy/assets/frameworks/__init__.py
eryx_deploy/assets/frameworks/abs_framework.py
eryx_deploy/assets/frameworks/django.py
eryx_deploy/assets/frameworks/ruby_on_rails.py
eryx_deploy/assets/language_environments/__init__.py
eryx_deploy/assets/language_environments/python/__init__.py
eryx_deploy/assets/language_environments/python/virtualenv.py
eryx_deploy/assets/language_environments/ruby/__init__.py
eryx_deploy/assets/language_environments/ruby/rbenv.py
eryx_deploy/assets/machines/__init__.py
eryx_deploy/assets/machines/abs_machine.py
eryx_deploy/assets/machines/amazon_rds.py
eryx_deploy/assets/machines/with_shell/__init__.py
eryx_deploy/assets/machines/with_shell/abs_with_shell.py
eryx_deploy/assets/machines/with_shell/ubuntu_machine.py
eryx_deploy/assets/package_managers/__init__.py
eryx_deploy/assets/package_managers/abs_package_manager.py
eryx_deploy/assets/package_managers/null.py
eryx_deploy/assets/package_managers/frontend/__init__.py
eryx_deploy/assets/package_managers/frontend/abs_frontend.py
eryx_deploy/assets/package_managers/frontend/npm.py
eryx_deploy/assets/package_managers/frontend/yarn.py
eryx_deploy/assets/package_managers/python/__init__.py
eryx_deploy/assets/package_managers/python/abs_python.py
eryx_deploy/assets/package_managers/python/pip.py
eryx_deploy/assets/package_managers/ruby/__init__.py
eryx_deploy/assets/package_managers/ruby/ruby_gems_with_bundler.py
eryx_deploy/assets/vcs/__init__.py
eryx_deploy/assets/vcs/git.py
eryxdeploy-0.4.7.dist-info/METADATA
eryxdeploy-0.4.7.dist-info/WHEEL
eryxdeploy-0.4.7.dist-info/top_level.txt
eryxdeploy-0.4.7.dist-info/RECORD
